ml_algo_automation/__init__.py
ml_algo_automation/ml_model_comparator.py
ml_algo_automation-0.1.5.dist-info/METADATA
ml_algo_automation-0.1.5.dist-info/WHEEL
ml_algo_automation-0.1.5.dist-info/top_level.txt
ml_algo_automation-0.1.5.dist-info/RECORD
