Metadata-Version: 2.1
Name: ml-algo-automation
Version: 0.1.5
Summary: A library for comparing regression and classification models using scikit-learn.
Home-page: https://github.com/gencay-strata/ml_automation
Author: Nathan Rosidi
Author-email: nate@stratascratch.com
Classifier: Programming Language :: Python :: 3
Classifier: License :: OSI Approved :: MIT License
Classifier: Operating System :: OS Independent
Requires-Python: >=3.6
Requires-Dist: scikit-learn
Requires-Dist: numpy
